bourbon/__init__.py
bourbon/models.py
bourbon/static/bourbon/_bourbon-deprecated-upcoming.scss
bourbon/static/bourbon/_bourbon.scss
bourbon/static/bourbon/addons/_button.scss
bourbon/static/bourbon/addons/_clearfix.scss
bourbon/static/bourbon/addons/_font-family.scss
bourbon/static/bourbon/addons/_hide-text.scss
bourbon/static/bourbon/addons/_html5-input-types.scss
bourbon/static/bourbon/addons/_position.scss
bourbon/static/bourbon/addons/_prefixer.scss
bourbon/static/bourbon/addons/_retina-image.scss
bourbon/static/bourbon/addons/_size.scss
bourbon/static/bourbon/addons/_timing-functions.scss
bourbon/static/bourbon/addons/_triangle.scss
bourbon/static/bourbon/css3/_animation.scss
bourbon/static/bourbon/css3/_appearance.scss
bourbon/static/bourbon/css3/_backface-visibility.scss
bourbon/static/bourbon/css3/_background-image.scss
bourbon/static/bourbon/css3/_background.scss
bourbon/static/bourbon/css3/_border-image.scss
bourbon/static/bourbon/css3/_border-radius.scss
bourbon/static/bourbon/css3/_box-sizing.scss
bourbon/static/bourbon/css3/_columns.scss
bourbon/static/bourbon/css3/_flex-box.scss
bourbon/static/bourbon/css3/_font-face.scss
bourbon/static/bourbon/css3/_hidpi-media-query.scss
bourbon/static/bourbon/css3/_image-rendering.scss
bourbon/static/bourbon/css3/_inline-block.scss
bourbon/static/bourbon/css3/_keyframes.scss
bourbon/static/bourbon/css3/_linear-gradient.scss
bourbon/static/bourbon/css3/_perspective.scss
bourbon/static/bourbon/css3/_placeholder.scss
bourbon/static/bourbon/css3/_radial-gradient.scss
bourbon/static/bourbon/css3/_transform.scss
bourbon/static/bourbon/css3/_transition.scss
bourbon/static/bourbon/css3/_user-select.scss
bourbon/static/bourbon/functions/_compact.scss
bourbon/static/bourbon/functions/_flex-grid.scss
bourbon/static/bourbon/functions/_grid-width.scss
bourbon/static/bourbon/functions/_linear-gradient.scss
bourbon/static/bourbon/functions/_modular-scale.scss
django_bourbon-3.1.8.dist-info/DESCRIPTION.rst
django_bourbon-3.1.8.dist-info/METADATA
django_bourbon-3.1.8.dist-info/pydist.json
django_bourbon-3.1.8.dist-info/RECORD
django_bourbon-3.1.8.dist-info/top_level.txt
django_bourbon-3.1.8.dist-info/WHEEL
